argparsebuilder/VERSION
argparsebuilder/__init__.py
argparsebuilder/_argparsebuilder.py
argparsebuilder-0.1.0.dist-info/LICENSE.txt
argparsebuilder-0.1.0.dist-info/METADATA
argparsebuilder-0.1.0.dist-info/WHEEL
argparsebuilder-0.1.0.dist-info/top_level.txt
argparsebuilder-0.1.0.dist-info/RECORD
